torch_segment/__init__.py
torch_segment/config.py
torch_segment/dataset.py
torch_segment/engine.py
torch_segment/test.py
torch_segment/train.py
torch_segment/models/__init__.py
torch_segment/models/fcn_resnet50.py
torch_segment/models/unet.py
torch_segment/models/unet11.py
torch_segment/utils/__init__.py
torch_segment/utils/helpers.py
torch_segment/utils/metrics.py
torch_segment-0.0.2.dist-info/LICENSE
torch_segment-0.0.2.dist-info/METADATA
torch_segment-0.0.2.dist-info/WHEEL
torch_segment-0.0.2.dist-info/top_level.txt
torch_segment-0.0.2.dist-info/RECORD
