Metadata-Version: 2.1
Name: torch-segment
Version: 0.0.2
Summary: A library for deep learning image segmentation using PyTorch
Home-page: https://github.com/sovit-123/Torch-Segment
Author: Sovit Ranjan Rath
Author-email: sovitrath5@gmail.com
License: UNKNOWN
Platform: UNKNOWN
Classifier: Programming Language :: Python :: 3
Classifier: License :: OSI Approved :: MIT License
Classifier: Operating System :: OS Independent
Requires-Python: >=3.7
